mkdocs_ini_includer/__init__.py
mkdocs_ini_includer/plugin.py
tests/__init__.py
tests/test_plugin.py
mkdocs_ini_includer-1.1.0.dist-info/METADATA
mkdocs_ini_includer-1.1.0.dist-info/WHEEL
mkdocs_ini_includer-1.1.0.dist-info/entry_points.txt
mkdocs_ini_includer-1.1.0.dist-info/top_level.txt
mkdocs_ini_includer-1.1.0.dist-info/RECORD
